oss_song2/__init__.py
oss_song2/test.py
oss_song2-0.0.1.dist-info/LICENSE
oss_song2-0.0.1.dist-info/METADATA
oss_song2-0.0.1.dist-info/WHEEL
oss_song2-0.0.1.dist-info/entry_points.txt
oss_song2-0.0.1.dist-info/top_level.txt
oss_song2-0.0.1.dist-info/RECORD
